<?xml version="1.0" encoding="utf-8"?>
<rdf:RDF xmlns:cim="http://iec.ch/TC57/2013/CIM-schema-cim16#" xmlns:entsoe="http://entsoe.eu/CIM/SchemaExtension/3/1#" xmlns:md="http://iec.ch/TC57/61970-552/ModelDescription/1#" xmlns:rdf="http://www.w3.org/1999/02/22-rdf-syntax-ns#">
  <md:FullModel rdf:about="urn:uuid:2399cvd3-9a39-11e0-aa80-0800200c9a66">
    <md:Model.scenarioTime>2030-01-02T09:00:00</md:Model.scenarioTime>
    <md:Model.created>2014-10-22T09:01:25.830</md:Model.created>
    <md:Model.description>CGMES Conformity Assessment: Mini Grid Type 2 Test Configuration. The model is owned by ENTSO-E and is provided by ENTSO-E "as it is". To the fullest extent permitted by law, ENTSO-E shall not be liable for any damages of any kind arising out of the use of the model (including any of its subsequent modifications). ENTSO-E neither warrants, nor represents that the use of the model will not infringe the rights of third parties. Any use of the model shall include a reference to ENTSO-E. ENTSO-E web site is the only official source of information related to the model.</md:Model.description>
    <md:Model.version>4</md:Model.version>
    <md:Model.profile>http://entsoe.eu/CIM/StateVariables/4/1</md:Model.profile>
    <md:Model.modelingAuthoritySet>http://A1.de/Planning/ENTSOE/2</md:Model.modelingAuthoritySet>
    <md:Model.Supersedes rdf:resource="urn:uuid:239vcbd3-9a39-11e0-aa80-0800200c9a66" />
    <md:Model.DependentOn rdf:resource="urn:uuid:2399ced2-9a39-11e0-aa80-0800200c9a66" />
    <md:Model.DependentOn rdf:resource="urn:uuid:2399ctd4-9a39-11e0-aa80-0800200c9a66" />
    <md:Model.DependentOn rdf:resource="urn:uuid:2399cbd1-9a39-11e0-aa80-0800200c9a66" />
  </md:FullModel>
  <cim:SvVoltage rdf:ID="_76bca92d-ccf1-47c0-b911-6d31cd5b1271">
    <cim:SvVoltage.angle>-0.02838281</cim:SvVoltage.angle>
    <cim:SvVoltage.v>380.740021</cim:SvVoltage.v>
    <cim:SvVoltage.TopologicalNode rdf:resource="#_adee76cd-b2b9-48ac-8fd4-0d205a435f59" />
  </cim:SvVoltage>
  <cim:SvVoltage rdf:ID="_287cb60c-fe18-488b-b9fa-5854048bfaab">
    <cim:SvVoltage.angle>-0.02838281</cim:SvVoltage.angle>
    <cim:SvVoltage.v>28.5555</cim:SvVoltage.v>
    <cim:SvVoltage.TopologicalNode rdf:resource="#_87c0d153-e308-4b2b-92a4-4fad53ab1ff9" />
  </cim:SvVoltage>
  <cim:SvVoltage rdf:ID="_51261d39-c119-43f0-afa5-25e0e7390159">
    <cim:SvVoltage.angle>-0.028382808</cim:SvVoltage.angle>
    <cim:SvVoltage.v>114.222008</cim:SvVoltage.v>
    <cim:SvVoltage.TopologicalNode rdf:resource="#_b3d3b4ad-02af-4490-8748-70f6c9a23734" />
  </cim:SvVoltage>
  <cim:SvVoltage rdf:ID="_9a10feaf-8063-43ce-b565-45cc66bd09ea">
    <cim:SvVoltage.angle>0</cim:SvVoltage.angle>
    <cim:SvVoltage.v>10</cim:SvVoltage.v>
    <cim:SvVoltage.TopologicalNode rdf:resource="#_c7eda3d2-e92d-4935-8166-5e045d3de045" />
  </cim:SvVoltage>
  <cim:SvVoltage rdf:ID="_273951bb-81c6-40e6-a3b7-337cb0f972d5">
    <cim:SvVoltage.angle>0.3332449</cim:SvVoltage.angle>
    <cim:SvVoltage.v>20.9227867</cim:SvVoltage.v>
    <cim:SvVoltage.TopologicalNode rdf:resource="#_7f5515b2-ca6b-45af-93ee-f196686f0c66" />
  </cim:SvVoltage>
  <cim:SvVoltage rdf:ID="_a8d33693-7169-45bc-b030-3092c7180c31">
    <cim:SvVoltage.angle>0.0287097786</cim:SvVoltage.angle>
    <cim:SvVoltage.v>114.313438</cim:SvVoltage.v>
    <cim:SvVoltage.TopologicalNode rdf:resource="#_c0adab49-d445-4609-a1a3-ebe4ef297cc8" />
  </cim:SvVoltage>
  <cim:SvVoltage rdf:ID="_f3bef8ae-c134-4226-8f68-00a8fc7fab86">
    <cim:SvVoltage.angle>-0.02838281</cim:SvVoltage.angle>
    <cim:SvVoltage.v>28.5555</cim:SvVoltage.v>
    <cim:SvVoltage.TopologicalNode rdf:resource="#_03163ede-7eec-457f-8641-365982227d7c" />
  </cim:SvVoltage>
  <cim:SvVoltage rdf:ID="_ee6bf4d8-34bb-47c9-9fc8-616e3e5f320c">
    <cim:SvVoltage.angle>-0.006085666</cim:SvVoltage.angle>
    <cim:SvVoltage.v>114.258179</cim:SvVoltage.v>
    <cim:SvVoltage.TopologicalNode rdf:resource="#_c8726716-e182-4373-b83e-8f60070078cb" />
  </cim:SvVoltage>
  <cim:SvVoltage rdf:ID="_d04492fc-d83a-4626-bacc-a6fce938fc31">
    <cim:SvVoltage.angle>-0.0311403517</cim:SvVoltage.angle>
    <cim:SvVoltage.v>114.2175</cim:SvVoltage.v>
    <cim:SvVoltage.TopologicalNode rdf:resource="#_37edd845-456f-4c3e-98d5-19af0c1cef1e" />
  </cim:SvVoltage>
  <cim:SvVoltage rdf:ID="_15fda5cb-d3c6-486d-a948-fcdc9bfec2a0">
    <cim:SvVoltage.angle>-0.585824847</cim:SvVoltage.angle>
    <cim:SvVoltage.v>10.3816137</cim:SvVoltage.v>
    <cim:SvVoltage.TopologicalNode rdf:resource="#_764e0b8a-f2af-4092-b6aa-b4a19e55db98" />
  </cim:SvVoltage>
  <cim:SvVoltage rdf:ID="_feccae00-19f3-4195-ba0c-85ff787363d3">
    <cim:SvVoltage.angle>-0.7814721</cim:SvVoltage.angle>
    <cim:SvVoltage.v>10.2678013</cim:SvVoltage.v>
    <cim:SvVoltage.TopologicalNode rdf:resource="#_cd84fa40-ef63-422d-8ee0-d0a0f806719e" />
  </cim:SvVoltage>
  <cim:SvVoltage rdf:ID="_e385ef50-9580-4489-a7de-e5ba0fc9ae7a">
    <cim:SvVoltage.angle>0</cim:SvVoltage.angle>
    <cim:SvVoltage.v>0</cim:SvVoltage.v>
    <cim:SvVoltage.TopologicalNode rdf:resource="#_8372a156-7579-4ea5-1111-24caf0d24603" />
  </cim:SvVoltage>
  <cim:SvVoltage rdf:ID="_f1cdcc0d-11dd-43a1-ad4f-c2d3a1f69830">
    <cim:SvVoltage.angle>0</cim:SvVoltage.angle>
    <cim:SvVoltage.v>0</cim:SvVoltage.v>
    <cim:SvVoltage.TopologicalNode rdf:resource="#_8372a156-7579-4ea5-2222-24caf0d24603" />
  </cim:SvVoltage>
  <cim:SvPowerFlow rdf:ID="_5973f1a9-2dee-4d6b-95ac-f1a8877dfdfd">
    <cim:SvPowerFlow.p>-0.0877826</cim:SvPowerFlow.p>
    <cim:SvPowerFlow.q>-0.178615972</cim:SvPowerFlow.q>
    <cim:SvPowerFlow.Terminal rdf:resource="#_4dec53ca-3ea6-4bd0-a225-b559c8293e91" />
  </cim:SvPowerFlow>
  <cim:SvPowerFlow rdf:ID="_af94d1f0-018a-4f72-96d7-c618bd31b0b3">
    <cim:SvPowerFlow.p>-5</cim:SvPowerFlow.p>
    <cim:SvPowerFlow.q>-2</cim:SvPowerFlow.q>
    <cim:SvPowerFlow.Terminal rdf:resource="#_3434b50d-677d-4ad5-96d7-6c7d1be611e6" />
  </cim:SvPowerFlow>
  <cim:SvPowerFlow rdf:ID="_610ca856-ed63-48b4-a536-d5d22ffe88a8">
    <cim:SvPowerFlow.p>-4</cim:SvPowerFlow.p>
    <cim:SvPowerFlow.q>-3</cim:SvPowerFlow.q>
    <cim:SvPowerFlow.Terminal rdf:resource="#_9165ded7-ec43-469a-b006-554d388a63ec" />
  </cim:SvPowerFlow>
  <cim:SvPowerFlow rdf:ID="_bed71976-11e5-432d-81c9-a6ae8369f5e2">
    <cim:SvPowerFlow.p>5</cim:SvPowerFlow.p>
    <cim:SvPowerFlow.q>3</cim:SvPowerFlow.q>
    <cim:SvPowerFlow.Terminal rdf:resource="#_e3420c0c-d6fc-49ee-9447-74c8e1eba64e" />
  </cim:SvPowerFlow>
  <cim:SvStatus rdf:ID="_ee7bc371-46be-4808-b0c5-94f54719dab0">
    <cim:SvStatus.inService>true</cim:SvStatus.inService>
    <cim:SvStatus.ConductingEquipment rdf:resource="#_2970a2b7-b840-4e9c-b405-0cb854cd2318" />
  </cim:SvStatus>
  <cim:SvStatus rdf:ID="_4c5f9b38-a0d5-4ca3-a9a0-68eb616ac788">
    <cim:SvStatus.inService>true</cim:SvStatus.inService>
    <cim:SvStatus.ConductingEquipment rdf:resource="#_ca67be42-750e-4ebf-bfaa-24d446e59a22" />
  </cim:SvStatus>
  <cim:SvStatus rdf:ID="_9502d86c-ae51-4fba-b393-b1ce3f5c2bc2">
    <cim:SvStatus.inService>true</cim:SvStatus.inService>
    <cim:SvStatus.ConductingEquipment rdf:resource="#_392ea173-4f8e-48fa-b2a3-5c3721e93196" />
  </cim:SvStatus>
  <cim:SvStatus rdf:ID="_63ad34c3-2e59-4ea9-941c-ceebcdbe1653">
    <cim:SvStatus.inService>true</cim:SvStatus.inService>
    <cim:SvStatus.ConductingEquipment rdf:resource="#_062ece1f-ade5-4d20-9c3a-fd8f12d12ec1" />
  </cim:SvStatus>
  <cim:SvStatus rdf:ID="_371ac229-3680-4802-a0cc-243a6233e1b9">
    <cim:SvStatus.inService>true</cim:SvStatus.inService>
    <cim:SvStatus.ConductingEquipment rdf:resource="#_ba62884d-8800-41a8-9c26-698297d7ebaa" />
  </cim:SvStatus>
  <cim:SvStatus rdf:ID="_5cf7fdc1-207f-4c43-9fdf-615c323f6cb6">
    <cim:SvStatus.inService>true</cim:SvStatus.inService>
    <cim:SvStatus.ConductingEquipment rdf:resource="#_f184d87b-5565-45ee-89b4-29e8a42d3ad1" />
  </cim:SvStatus>
  <cim:SvStatus rdf:ID="_7c4719cd-105d-4f4f-af30-27ee08afaac6">
    <cim:SvStatus.inService>true</cim:SvStatus.inService>
    <cim:SvStatus.ConductingEquipment rdf:resource="#_089c1945-4101-487f-a557-66c013b748f6" />
  </cim:SvStatus>
  <cim:SvStatus rdf:ID="_d919453b-da07-42ba-9e23-d78b6bff0caf">
    <cim:SvStatus.inService>true</cim:SvStatus.inService>
    <cim:SvStatus.ConductingEquipment rdf:resource="#_3de9e1ad-4562-44df-b268-70ed0517e9e7" />
  </cim:SvStatus>
  <cim:SvStatus rdf:ID="_69480977-34b6-4203-a6e9-44a2f1b1c4b3">
    <cim:SvStatus.inService>true</cim:SvStatus.inService>
    <cim:SvStatus.ConductingEquipment rdf:resource="#_1e7f52a9-21d0-4ebe-9a8a-b29281d5bfc9" />
  </cim:SvStatus>
  <cim:SvStatus rdf:ID="_e54f1d29-4971-4b3d-b376-6cc1cfd94edb">
    <cim:SvStatus.inService>true</cim:SvStatus.inService>
    <cim:SvStatus.ConductingEquipment rdf:resource="#_56757c2b-550e-4843-886a-ed193f6eb21e" />
  </cim:SvStatus>
  <cim:SvStatus rdf:ID="_59df5698-9344-4b33-bd6c-b3e9e2ce9f21">
    <cim:SvStatus.inService>true</cim:SvStatus.inService>
    <cim:SvStatus.ConductingEquipment rdf:resource="#_e95a6228-ceac-4f0a-8b52-d35367b364dc" />
  </cim:SvStatus>
  <cim:SvStatus rdf:ID="_a9f07c4d-9e0b-4dbc-b929-caf394cd4f59">
    <cim:SvStatus.inService>true</cim:SvStatus.inService>
    <cim:SvStatus.ConductingEquipment rdf:resource="#_d5d1cc4a-6297-4386-b6ce-16dc26f15feb" />
  </cim:SvStatus>
  <cim:SvStatus rdf:ID="_562edf4a-8dc4-4c1c-849b-20c668ed9f1f">
    <cim:SvStatus.inService>true</cim:SvStatus.inService>
    <cim:SvStatus.ConductingEquipment rdf:resource="#_efdd7f46-67e6-46e3-9dcd-a3b6f8c613a4" />
  </cim:SvStatus>
  <cim:SvStatus rdf:ID="_429f6483-0c2f-443a-8b89-4b23973a2e2d">
    <cim:SvStatus.inService>true</cim:SvStatus.inService>
    <cim:SvStatus.ConductingEquipment rdf:resource="#_35df6abe-3087-4c27-a90a-12b5065333f3" />
  </cim:SvStatus>
  <cim:SvStatus rdf:ID="_637320f7-9977-47b9-bac2-278047971b9d">
    <cim:SvStatus.inService>true</cim:SvStatus.inService>
    <cim:SvStatus.ConductingEquipment rdf:resource="#_05597934-b248-491e-803a-68ce6290f502" />
  </cim:SvStatus>
  <cim:SvStatus rdf:ID="_391d5de4-d172-4246-974d-4f28c39a72c5">
    <cim:SvStatus.inService>true</cim:SvStatus.inService>
    <cim:SvStatus.ConductingEquipment rdf:resource="#_ceb5d06a-a7ff-4102-a620-7f3ea5fb4a51" />
  </cim:SvStatus>
  <cim:SvStatus rdf:ID="_2777b244-550e-4667-b116-3f2b68df44a9">
    <cim:SvStatus.inService>true</cim:SvStatus.inService>
    <cim:SvStatus.ConductingEquipment rdf:resource="#_6c89588b-3df5-4120-88e5-26164afb43e9" />
  </cim:SvStatus>
  <cim:SvStatus rdf:ID="_f4c4e48f-759f-47d8-a793-fed7b234337d">
    <cim:SvStatus.inService>true</cim:SvStatus.inService>
    <cim:SvStatus.ConductingEquipment rdf:resource="#_f1e72854-ec35-46e9-b614-27db354e8dbb" />
  </cim:SvStatus>
  <cim:SvStatus rdf:ID="_aaba3760-349a-489a-bf96-ff89d34b76bd">
    <cim:SvStatus.inService>true</cim:SvStatus.inService>
    <cim:SvStatus.ConductingEquipment rdf:resource="#_813365c3-5be7-4ef0-a0a7-abd1ae6dc174" />
  </cim:SvStatus>
  <cim:SvStatus rdf:ID="_2f923645-85bd-43e4-a334-7f43bc08d4bf">
    <cim:SvStatus.inService>true</cim:SvStatus.inService>
    <cim:SvStatus.ConductingEquipment rdf:resource="#_411b5401-0a43-404a-acb4-05c3d7d0c95c" />
  </cim:SvStatus>
  <cim:SvStatus rdf:ID="_9b227461-1ad8-403e-813b-0e6f194b99bf">
    <cim:SvStatus.inService>true</cim:SvStatus.inService>
    <cim:SvStatus.ConductingEquipment rdf:resource="#_5d38b7ed-73fd-405a-9cdb-78425e003773" />
  </cim:SvStatus>
  <cim:SvStatus rdf:ID="_b7be27a7-71fb-4480-951c-28340d7d6302">
    <cim:SvStatus.inService>false</cim:SvStatus.inService>
    <cim:SvStatus.ConductingEquipment rdf:resource="#_5150a037-e241-421f-98b2-fe60e5c90303" />
  </cim:SvStatus>
  <cim:SvStatus rdf:ID="_7cdca0f9-07eb-49d1-adc0-b98ed1509cb1">
    <cim:SvStatus.inService>false</cim:SvStatus.inService>
    <cim:SvStatus.ConductingEquipment rdf:resource="#_f32baf36-7ea3-4b6a-9452-71e7f18779f8" />
  </cim:SvStatus>
  <cim:SvStatus rdf:ID="_bf571490-4f1c-4985-8955-cec4e16ca027">
    <cim:SvStatus.inService>false</cim:SvStatus.inService>
    <cim:SvStatus.ConductingEquipment rdf:resource="#_1a89e8aa-04e8-4640-adf2-bcb07b18045d" />
  </cim:SvStatus>
  <cim:SvStatus rdf:ID="_10426fe3-3733-4603-954c-2d14ffb48084">
    <cim:SvStatus.inService>true</cim:SvStatus.inService>
    <cim:SvStatus.ConductingEquipment rdf:resource="#_5938ea51-0cfb-4c6c-8d6f-c2bf3254c94a" />
  </cim:SvStatus>
  <cim:SvStatus rdf:ID="_e05a8b6b-553a-4569-a070-bd1f338ebb61">
    <cim:SvStatus.inService>true</cim:SvStatus.inService>
    <cim:SvStatus.ConductingEquipment rdf:resource="#_5e9f0079-647e-46da-b0ee-f5f24e127602" />
  </cim:SvStatus>
  <cim:SvStatus rdf:ID="_82ec762e-6e70-4c9d-9171-70e2761f33b5">
    <cim:SvStatus.inService>true</cim:SvStatus.inService>
    <cim:SvStatus.ConductingEquipment rdf:resource="#_4580fb7b-c31b-4b84-ad1d-1ca4d50f4fc5" />
  </cim:SvStatus>
  <cim:SvStatus rdf:ID="_51f91c4f-9465-4705-8870-817e6e3aa661">
    <cim:SvStatus.inService>false</cim:SvStatus.inService>
    <cim:SvStatus.ConductingEquipment rdf:resource="#_da8e9cec-96f8-4048-b31a-a56f5ef53c31" />
  </cim:SvStatus>
  <cim:SvStatus rdf:ID="_1bcd819c-3f38-4f1f-aff8-d3afeb906f33">
    <cim:SvStatus.inService>true</cim:SvStatus.inService>
    <cim:SvStatus.ConductingEquipment rdf:resource="#_3006c97d-d51e-4e7b-92b1-a9a321f585ce" />
  </cim:SvStatus>
  <cim:SvStatus rdf:ID="_6a4fd830-365f-488e-ad60-c23c3a3820ac">
    <cim:SvStatus.inService>true</cim:SvStatus.inService>
    <cim:SvStatus.ConductingEquipment rdf:resource="#_622a9aff-f9d4-49c7-8f29-fd88009c5df0" />
  </cim:SvStatus>
  <cim:SvStatus rdf:ID="_3fb6b722-cab6-4b88-acbd-ea68f6a26862">
    <cim:SvStatus.inService>true</cim:SvStatus.inService>
    <cim:SvStatus.ConductingEquipment rdf:resource="#_f5335138-f3b9-400b-abf1-e9b559c887b2" />
  </cim:SvStatus>
  <cim:SvStatus rdf:ID="_d2a005ff-216d-427e-8072-799cc0202293">
    <cim:SvStatus.inService>false</cim:SvStatus.inService>
    <cim:SvStatus.ConductingEquipment rdf:resource="#_84a0d591-e69e-407d-991d-54b3c6394d09" />
  </cim:SvStatus>
  <cim:SvStatus rdf:ID="_44465f6e-27ae-4cb6-bef8-aa0d500b2202">
    <cim:SvStatus.inService>true</cim:SvStatus.inService>
    <cim:SvStatus.ConductingEquipment rdf:resource="#_7d655d91-394a-4f47-8f83-7f1de3baa056" />
  </cim:SvStatus>
  <cim:SvStatus rdf:ID="_f968e22c-f756-4576-800b-ec4ffc43e0dd">
    <cim:SvStatus.inService>true</cim:SvStatus.inService>
    <cim:SvStatus.ConductingEquipment rdf:resource="#_4c49cfd1-4758-476e-95ce-5cd2c56e3165" />
  </cim:SvStatus>
  <cim:SvStatus rdf:ID="_10dff5bd-08ea-46f6-805c-b4f697ba8879">
    <cim:SvStatus.inService>true</cim:SvStatus.inService>
    <cim:SvStatus.ConductingEquipment rdf:resource="#_dcba20ce-b619-471a-8ab0-2371d4d090b0" />
  </cim:SvStatus>
  <cim:SvStatus rdf:ID="_7e2c2e41-2691-4391-bf2e-7be4829bab22">
    <cim:SvStatus.inService>false</cim:SvStatus.inService>
    <cim:SvStatus.ConductingEquipment rdf:resource="#_4171593e-40e0-4937-8c04-2276c3c16d68" />
  </cim:SvStatus>
  <cim:SvStatus rdf:ID="_ad8d5aed-59bc-4a95-867c-2d5e85d3b064">
    <cim:SvStatus.inService>true</cim:SvStatus.inService>
    <cim:SvStatus.ConductingEquipment rdf:resource="#_3a783d1d-1113-414d-ab67-34b139781196" />
  </cim:SvStatus>
  <cim:SvStatus rdf:ID="_13da1f92-d77c-46a3-827e-b4d62d06303e">
    <cim:SvStatus.inService>true</cim:SvStatus.inService>
    <cim:SvStatus.ConductingEquipment rdf:resource="#_fbdcf00d-8a07-4c62-9e39-86f459bea2be" />
  </cim:SvStatus>
  <cim:SvStatus rdf:ID="_f1d265ba-7d1a-48f7-94ca-89372bf9fa4e">
    <cim:SvStatus.inService>true</cim:SvStatus.inService>
    <cim:SvStatus.ConductingEquipment rdf:resource="#_83317cbd-8326-44b8-a9fb-f69b6ba5a1cb" />
  </cim:SvStatus>
  <cim:SvStatus rdf:ID="_db10c16d-cd9a-451c-97ce-598fdc174f31">
    <cim:SvStatus.inService>true</cim:SvStatus.inService>
    <cim:SvStatus.ConductingEquipment rdf:resource="#_fe1384c9-f1c1-4026-9f5d-10a3b22208b9" />
  </cim:SvStatus>
  <cim:SvStatus rdf:ID="_375df6f8-718e-4ada-80b9-27bbbd7c834e">
    <cim:SvStatus.inService>true</cim:SvStatus.inService>
    <cim:SvStatus.ConductingEquipment rdf:resource="#_2ed632f6-36a3-4937-8d5d-ad105c57c071" />
  </cim:SvStatus>
  <cim:SvStatus rdf:ID="_9973184e-0ffb-4708-89b1-cd937a7318bb">
    <cim:SvStatus.inService>true</cim:SvStatus.inService>
    <cim:SvStatus.ConductingEquipment rdf:resource="#_154f3756-4e07-4f06-9147-ed83de84e265" />
  </cim:SvStatus>
  <cim:SvStatus rdf:ID="_19c5243c-dfe5-462c-94e0-141fed9a2e25">
    <cim:SvStatus.inService>false</cim:SvStatus.inService>
    <cim:SvStatus.ConductingEquipment rdf:resource="#_78f2ae0e-da25-483a-8a71-76f709389894" />
  </cim:SvStatus>
  <cim:SvStatus rdf:ID="_df846aa0-71cd-4fab-8f6d-fc4cb8cf5e62">
    <cim:SvStatus.inService>true</cim:SvStatus.inService>
    <cim:SvStatus.ConductingEquipment rdf:resource="#_15d6eb77-36d6-48d0-a227-25d29e839517" />
  </cim:SvStatus>
  <cim:SvStatus rdf:ID="_373d510c-7351-4321-adb2-cd070b7f6e5c">
    <cim:SvStatus.inService>true</cim:SvStatus.inService>
    <cim:SvStatus.ConductingEquipment rdf:resource="#_a9b68255-188c-408d-8362-5f3b0a1e730f" />
  </cim:SvStatus>
  <cim:SvStatus rdf:ID="_ec319a8b-99c4-403f-b475-e1341d98d186">
    <cim:SvStatus.inService>true</cim:SvStatus.inService>
    <cim:SvStatus.ConductingEquipment rdf:resource="#_84970563-073f-4316-a175-060b544640e0" />
  </cim:SvStatus>
  <cim:SvStatus rdf:ID="_555a1dae-6f52-48e7-9f6d-7d61102d8447">
    <cim:SvStatus.inService>false</cim:SvStatus.inService>
    <cim:SvStatus.ConductingEquipment rdf:resource="#_bbbfc5c0-45ee-49fd-9dec-17c90af3f42b" />
  </cim:SvStatus>
  <cim:SvStatus rdf:ID="_ade3a012-2049-4727-a99c-cae1dc6f8fad">
    <cim:SvStatus.inService>true</cim:SvStatus.inService>
    <cim:SvStatus.ConductingEquipment rdf:resource="#_ea5a6982-018c-4ce6-85f6-78b5ab5dbfc1" />
  </cim:SvStatus>
  <cim:SvStatus rdf:ID="_88bd5e57-c697-484d-b01c-c92f9a2f6f8c">
    <cim:SvStatus.inService>true</cim:SvStatus.inService>
    <cim:SvStatus.ConductingEquipment rdf:resource="#_62156fd8-595d-4ab0-af53-0de3b8056a6e" />
  </cim:SvStatus>
  <cim:SvStatus rdf:ID="_589e5291-672a-42dd-8877-0fa04f9e356a">
    <cim:SvStatus.inService>true</cim:SvStatus.inService>
    <cim:SvStatus.ConductingEquipment rdf:resource="#_f88b1d2b-2f06-44ff-bfe5-8f1156e13092" />
  </cim:SvStatus>
  <cim:SvStatus rdf:ID="_baecb0e4-4a65-4b8d-8ec6-9b0b30d4edcb">
    <cim:SvStatus.inService>true</cim:SvStatus.inService>
    <cim:SvStatus.ConductingEquipment rdf:resource="#_faf75564-a154-4528-9428-913e6501a21f" />
  </cim:SvStatus>
  <cim:SvStatus rdf:ID="_32ffb284-0a76-437d-a05c-09cd41ef17ac">
    <cim:SvStatus.inService>true</cim:SvStatus.inService>
    <cim:SvStatus.ConductingEquipment rdf:resource="#_285ccb1e-a867-4efc-880e-e871c1929376" />
  </cim:SvStatus>
  <cim:SvStatus rdf:ID="_3c158ff9-ac67-4be8-a265-9ed6ac70af4a">
    <cim:SvStatus.inService>true</cim:SvStatus.inService>
    <cim:SvStatus.ConductingEquipment rdf:resource="#_22e27c40-eb38-4f04-aebd-7ef543798211" />
  </cim:SvStatus>
  <cim:SvStatus rdf:ID="_7b7f2428-da17-4cf2-a7cd-e4fc1acca797">
    <cim:SvStatus.inService>true</cim:SvStatus.inService>
    <cim:SvStatus.ConductingEquipment rdf:resource="#_9313f8a4-159d-48c8-92f1-36b1d16ee7c9" />
  </cim:SvStatus>
  <cim:SvStatus rdf:ID="_434c340f-138c-4d40-8f9e-3bb179682f7a">
    <cim:SvStatus.inService>true</cim:SvStatus.inService>
    <cim:SvStatus.ConductingEquipment rdf:resource="#_8e57f735-6869-463e-959e-b517b15a5ec5" />
  </cim:SvStatus>
  <cim:SvStatus rdf:ID="_15feb653-753e-4a94-b1ce-8bb5eb30c2f9">
    <cim:SvStatus.inService>true</cim:SvStatus.inService>
    <cim:SvStatus.ConductingEquipment rdf:resource="#_869b6ad5-3975-49ae-81fe-01547a229a25" />
  </cim:SvStatus>
  <cim:SvStatus rdf:ID="_9d37ac10-0379-4549-8040-8850e73ac901">
    <cim:SvStatus.inService>true</cim:SvStatus.inService>
    <cim:SvStatus.ConductingEquipment rdf:resource="#_8fa214d6-5b7f-4d04-8de7-e5609d9f9deb" />
  </cim:SvStatus>
  <cim:SvStatus rdf:ID="_5f8d7bb7-9a91-4e40-b12c-dc42814e93cf">
    <cim:SvStatus.inService>true</cim:SvStatus.inService>
    <cim:SvStatus.ConductingEquipment rdf:resource="#_eb33e134-698f-4258-8361-4b5fa4c2f9de" />
  </cim:SvStatus>
  <cim:SvStatus rdf:ID="_47edee7f-3e36-44b7-bdef-69e62d73abea">
    <cim:SvStatus.inService>true</cim:SvStatus.inService>
    <cim:SvStatus.ConductingEquipment rdf:resource="#_9e8afc23-52fc-40e6-ab85-3d0328a228f2" />
  </cim:SvStatus>
  <cim:SvStatus rdf:ID="_48a0e4e2-ee0a-43ef-96bc-422701d5f67b">
    <cim:SvStatus.inService>true</cim:SvStatus.inService>
    <cim:SvStatus.ConductingEquipment rdf:resource="#_90e1b509-e6d1-4a3b-8dcc-587f8b362bd3" />
  </cim:SvStatus>
  <cim:SvStatus rdf:ID="_bae929bf-8d13-4b3e-83f1-7d9027c736e3">
    <cim:SvStatus.inService>true</cim:SvStatus.inService>
    <cim:SvStatus.ConductingEquipment rdf:resource="#_788bb5ff-f36e-406b-b6a6-ea1b7268ba03" />
  </cim:SvStatus>
  <cim:SvStatus rdf:ID="_b786d756-196b-47cd-8fd0-03f06521154e">
    <cim:SvStatus.inService>true</cim:SvStatus.inService>
    <cim:SvStatus.ConductingEquipment rdf:resource="#_ef2f27d9-acde-4aad-a920-d61c98682f4d" />
  </cim:SvStatus>
  <cim:SvStatus rdf:ID="_30befc98-25ef-40b2-9e52-eca2675c9f96">
    <cim:SvStatus.inService>true</cim:SvStatus.inService>
    <cim:SvStatus.ConductingEquipment rdf:resource="#_b68ac335-9806-4609-812c-1f47f8738bde" />
  </cim:SvStatus>
  <cim:SvStatus rdf:ID="_8c0dc8c9-bc5a-4eb4-a138-055b46e53eeb">
    <cim:SvStatus.inService>true</cim:SvStatus.inService>
    <cim:SvStatus.ConductingEquipment rdf:resource="#_a5a962a6-2f47-4ef1-960f-e29131bcba36" />
  </cim:SvStatus>
  <cim:SvStatus rdf:ID="_5da22182-2137-4259-bdea-729657aa212e">
    <cim:SvStatus.inService>true</cim:SvStatus.inService>
    <cim:SvStatus.ConductingEquipment rdf:resource="#_b0677acc-df2e-4730-9516-fab2403103d0" />
  </cim:SvStatus>
  <cim:SvStatus rdf:ID="_756835c7-7eaf-4231-b18a-ecc2ecc1c6ea">
    <cim:SvStatus.inService>true</cim:SvStatus.inService>
    <cim:SvStatus.ConductingEquipment rdf:resource="#_b81c76fd-24fb-4888-a52e-5a9d0177df1d" />
  </cim:SvStatus>
  <cim:SvStatus rdf:ID="_65e9ad59-eec1-4c01-838f-ab0e0d168f0d">
    <cim:SvStatus.inService>true</cim:SvStatus.inService>
    <cim:SvStatus.ConductingEquipment rdf:resource="#_f58f46ea-b73b-421e-9fea-a86126a95b10" />
  </cim:SvStatus>
  <cim:SvStatus rdf:ID="_e9b4956f-69e2-4a3a-91c7-9c1579b48efa">
    <cim:SvStatus.inService>true</cim:SvStatus.inService>
    <cim:SvStatus.ConductingEquipment rdf:resource="#_06917aa0-6cc2-4d46-b37b-6ed9fec32ccd" />
  </cim:SvStatus>
  <cim:SvStatus rdf:ID="_9c46c9e3-df73-4c3f-a822-88f366b57f24">
    <cim:SvStatus.inService>true</cim:SvStatus.inService>
    <cim:SvStatus.ConductingEquipment rdf:resource="#_c6727598-4dae-4226-a542-166766d2f702" />
  </cim:SvStatus>
  <cim:SvStatus rdf:ID="_ba04338e-13c6-4733-bce1-0b7f9f2debca">
    <cim:SvStatus.inService>true</cim:SvStatus.inService>
    <cim:SvStatus.ConductingEquipment rdf:resource="#_c217742e-f713-44b7-a0b2-7c78aebc165d" />
  </cim:SvStatus>
  <cim:SvStatus rdf:ID="_0f963b52-d2d5-4c2e-98a3-466f35efbca7">
    <cim:SvStatus.inService>true</cim:SvStatus.inService>
    <cim:SvStatus.ConductingEquipment rdf:resource="#_6f28743a-c690-4569-b229-977566414a16" />
  </cim:SvStatus>
  <cim:SvStatus rdf:ID="_2d0acb00-22b2-494f-9701-a5f5267b0dd5">
    <cim:SvStatus.inService>true</cim:SvStatus.inService>
    <cim:SvStatus.ConductingEquipment rdf:resource="#_79341979-e66c-4b08-8053-6d97216e0777" />
  </cim:SvStatus>
  <cim:SvStatus rdf:ID="_63381e3a-b13b-46c7-8bd0-b75c1d110b43">
    <cim:SvStatus.inService>true</cim:SvStatus.inService>
    <cim:SvStatus.ConductingEquipment rdf:resource="#_a772f653-51f9-498c-afc9-c37b2a49cf32" />
  </cim:SvStatus>
  <cim:SvStatus rdf:ID="_fb36bd28-9793-4ecd-b7ac-a5d3c6052013">
    <cim:SvStatus.inService>true</cim:SvStatus.inService>
    <cim:SvStatus.ConductingEquipment rdf:resource="#_74534b01-b13b-49a2-b0d7-d0feb1348ef5" />
  </cim:SvStatus>
  <cim:SvStatus rdf:ID="_1f9d4e6e-b9fa-4ccd-b638-dba488b664fe">
    <cim:SvStatus.inService>true</cim:SvStatus.inService>
    <cim:SvStatus.ConductingEquipment rdf:resource="#_c7f7f032-1e4d-494a-9352-bad1a3056e3f" />
  </cim:SvStatus>
  <cim:SvStatus rdf:ID="_0c31c2a8-9596-40b3-8d86-18db09812360">
    <cim:SvStatus.inService>true</cim:SvStatus.inService>
    <cim:SvStatus.ConductingEquipment rdf:resource="#_c1e02075-4fdf-41e1-b5e4-925bb2396011" />
  </cim:SvStatus>
  <cim:SvStatus rdf:ID="_ff7fbd18-b40d-47ff-a8f6-3d00ee5408b2">
    <cim:SvStatus.inService>true</cim:SvStatus.inService>
    <cim:SvStatus.ConductingEquipment rdf:resource="#_2ec6cb16-7516-46f9-8cd8-2a52eea85bb5" />
  </cim:SvStatus>
  <cim:SvStatus rdf:ID="_97a6469c-0858-4ab4-93a4-06be2e2873c6">
    <cim:SvStatus.inService>true</cim:SvStatus.inService>
    <cim:SvStatus.ConductingEquipment rdf:resource="#_c803aa12-a8c7-4491-8163-1a1c6ea60db8" />
  </cim:SvStatus>
  <cim:SvStatus rdf:ID="_0e16e1ca-d6f1-47f7-884d-c24b89ad4377">
    <cim:SvStatus.inService>true</cim:SvStatus.inService>
    <cim:SvStatus.ConductingEquipment rdf:resource="#_6557ecb5-b9a7-4089-aa70-58d4d11f503b" />
  </cim:SvStatus>
  <cim:SvStatus rdf:ID="_e4617582-dc47-4370-9ad2-f20f43d26d2b">
    <cim:SvStatus.inService>true</cim:SvStatus.inService>
    <cim:SvStatus.ConductingEquipment rdf:resource="#_ac85d2fb-2417-4a86-9c63-d389e6ffae47" />
  </cim:SvStatus>
  <cim:SvStatus rdf:ID="_c248d437-b6ae-4987-8c72-3cb9d8cc6bfa">
    <cim:SvStatus.inService>true</cim:SvStatus.inService>
    <cim:SvStatus.ConductingEquipment rdf:resource="#_2c03a3cf-4890-4092-9fe3-c6d139677882" />
  </cim:SvStatus>
  <cim:SvStatus rdf:ID="_e88232b3-eeac-4f4c-8f63-c58ecd411308">
    <cim:SvStatus.inService>true</cim:SvStatus.inService>
    <cim:SvStatus.ConductingEquipment rdf:resource="#_d0119330-220f-4ed3-ad3c-f893ad0534fb" />
  </cim:SvStatus>
  <cim:SvStatus rdf:ID="_d920fd0c-6e42-410c-be5b-9ea0fbb61c5d">
    <cim:SvStatus.inService>true</cim:SvStatus.inService>
    <cim:SvStatus.ConductingEquipment rdf:resource="#_64b4c3d3-0116-4477-af5f-76fe482a4347" />
  </cim:SvStatus>
  <cim:SvStatus rdf:ID="_13d3b8cc-0952-4e81-b7a1-c2cf4ebd24d4">
    <cim:SvStatus.inService>true</cim:SvStatus.inService>
    <cim:SvStatus.ConductingEquipment rdf:resource="#_9dc3bedf-0d30-4a56-ba5c-f2e69d7997ee" />
  </cim:SvStatus>
  <cim:SvStatus rdf:ID="_c46bb623-b869-4afb-ba46-a9633c268980">
    <cim:SvStatus.inService>true</cim:SvStatus.inService>
    <cim:SvStatus.ConductingEquipment rdf:resource="#_d6665f59-851b-4183-81b0-59c53e1baa6a" />
  </cim:SvStatus>
  <cim:SvStatus rdf:ID="_c8208c97-a3c2-41d0-bfe5-eab393619862">
    <cim:SvStatus.inService>true</cim:SvStatus.inService>
    <cim:SvStatus.ConductingEquipment rdf:resource="#_b8924fbf-6513-4385-b032-21045c0a5b8f" />
  </cim:SvStatus>
  <cim:SvStatus rdf:ID="_2c999800-6799-4e33-b5d8-bef28b7db711">
    <cim:SvStatus.inService>false</cim:SvStatus.inService>
    <cim:SvStatus.ConductingEquipment rdf:resource="#_25781dc3-bf27-4b5d-b920-e71f246bcde6" />
  </cim:SvStatus>
  <cim:SvStatus rdf:ID="_b8738cd2-7074-4163-bdcb-7fe5c272e79f">
    <cim:SvStatus.inService>true</cim:SvStatus.inService>
    <cim:SvStatus.ConductingEquipment rdf:resource="#_cd8813aa-3213-4d9a-994d-4a4513e458b4" />
  </cim:SvStatus>
  <cim:SvStatus rdf:ID="_3b105da7-0972-465f-a2bc-346969823042">
    <cim:SvStatus.inService>true</cim:SvStatus.inService>
    <cim:SvStatus.ConductingEquipment rdf:resource="#_1287758d-606d-44c9-9e93-2f465ebf54b7" />
  </cim:SvStatus>
  <cim:SvStatus rdf:ID="_fabc3634-dc7b-444a-847d-7a558eef9c1e">
    <cim:SvStatus.inService>true</cim:SvStatus.inService>
    <cim:SvStatus.ConductingEquipment rdf:resource="#_8e56ead3-f4d3-4cd9-a34f-c7340ff7384d" />
  </cim:SvStatus>
  <cim:SvStatus rdf:ID="_443228e3-22b4-4428-84fa-e8842c49b0b1">
    <cim:SvStatus.inService>false</cim:SvStatus.inService>
    <cim:SvStatus.ConductingEquipment rdf:resource="#_a43ab51f-ba09-4224-8437-63a9ab30ea50" />
  </cim:SvStatus>
  <cim:SvStatus rdf:ID="_6e81de56-d166-42b6-8a4f-649cd9e1fd33">
    <cim:SvStatus.inService>true</cim:SvStatus.inService>
    <cim:SvStatus.ConductingEquipment rdf:resource="#_b7e79b65-8d3e-4ee9-bf05-12bf2250b12d" />
  </cim:SvStatus>
  <cim:SvStatus rdf:ID="_3a8d1ea1-18f7-4405-9218-03098a7d8035">
    <cim:SvStatus.inService>true</cim:SvStatus.inService>
    <cim:SvStatus.ConductingEquipment rdf:resource="#_052682ba-a4e5-41d5-9728-0fa4e2e01011" />
  </cim:SvStatus>
  <cim:SvStatus rdf:ID="_4937c7b5-02c5-415c-b152-6f58f17e3911">
    <cim:SvStatus.inService>true</cim:SvStatus.inService>
    <cim:SvStatus.ConductingEquipment rdf:resource="#_2af10fbd-4763-4940-b11d-00dcd7627016" />
  </cim:SvStatus>
  <cim:SvStatus rdf:ID="_ce6b10be-bea6-4cd4-bb9d-8c9ab87e08ab">
    <cim:SvStatus.inService>true</cim:SvStatus.inService>
    <cim:SvStatus.ConductingEquipment rdf:resource="#_27cb23c0-ad7b-4019-8cdf-205e240f742a" />
  </cim:SvStatus>
  <cim:SvStatus rdf:ID="_2e338f31-ee5b-4b8a-a22d-0a9fcecc86c4">
    <cim:SvStatus.inService>true</cim:SvStatus.inService>
    <cim:SvStatus.ConductingEquipment rdf:resource="#_fdf5cfbe-9bf5-406a-8d04-fafe47afe31d" />
  </cim:SvStatus>
  <cim:SvStatus rdf:ID="_26501a87-e469-4001-aa9c-b82c9debd00e">
    <cim:SvStatus.inService>true</cim:SvStatus.inService>
    <cim:SvStatus.ConductingEquipment rdf:resource="#_2791a96c-c66c-44e7-a5dc-8331a8996c76" />
  </cim:SvStatus>
  <cim:SvStatus rdf:ID="_0207b64e-2cdb-4c0d-827b-380683a9a854">
    <cim:SvStatus.inService>false</cim:SvStatus.inService>
    <cim:SvStatus.ConductingEquipment rdf:resource="#_0e851b9d-f638-40ff-b77a-b381698dc9a3" />
  </cim:SvStatus>
  <cim:SvStatus rdf:ID="_e64412cf-ba23-4198-af3f-560f61a7438d">
    <cim:SvStatus.inService>true</cim:SvStatus.inService>
    <cim:SvStatus.ConductingEquipment rdf:resource="#_c8b06b9b-8876-4fb5-9279-5a396e3db63d" />
  </cim:SvStatus>
  <cim:SvStatus rdf:ID="_8535fe49-27c1-4682-a21f-d2ae63911cc4">
    <cim:SvStatus.inService>true</cim:SvStatus.inService>
    <cim:SvStatus.ConductingEquipment rdf:resource="#_47143596-5947-430d-b14b-e00ac796985a" />
  </cim:SvStatus>
  <cim:SvStatus rdf:ID="_4999a65b-0f10-4b8e-9fd5-8fca6ae2fe6e">
    <cim:SvStatus.inService>true</cim:SvStatus.inService>
    <cim:SvStatus.ConductingEquipment rdf:resource="#_cf48defa-93b9-4723-8e41-8dab315ceee0" />
  </cim:SvStatus>
  <cim:SvStatus rdf:ID="_aef2fa45-1826-47db-8d10-486ef007dedc">
    <cim:SvStatus.inService>true</cim:SvStatus.inService>
    <cim:SvStatus.ConductingEquipment rdf:resource="#_cb5d0327-ad13-4b40-a74c-3d9888823205" />
  </cim:SvStatus>
  <cim:SvStatus rdf:ID="_9d65a23e-5174-42df-9c87-3555553b6d0b">
    <cim:SvStatus.inService>true</cim:SvStatus.inService>
    <cim:SvStatus.ConductingEquipment rdf:resource="#_d08c1582-0b3e-46ec-9e97-d70c423eefe1" />
  </cim:SvStatus>
  <cim:SvStatus rdf:ID="_d989089c-30bd-4524-a8f3-66e0a2c40a0c">
    <cim:SvStatus.inService>true</cim:SvStatus.inService>
    <cim:SvStatus.ConductingEquipment rdf:resource="#_ba645318-e12c-4f6a-b5e9-5dfe595ae477" />
  </cim:SvStatus>
  <cim:SvStatus rdf:ID="_bae8f029-44ad-42c5-b5d1-19066e166c6f">
    <cim:SvStatus.inService>false</cim:SvStatus.inService>
    <cim:SvStatus.ConductingEquipment rdf:resource="#_839c01c8-f8b8-45c0-aa2a-ba0a1a4b7504" />
  </cim:SvStatus>
  <cim:SvStatus rdf:ID="_64926ad9-a81f-4159-b23d-5c3cecf412af">
    <cim:SvStatus.inService>true</cim:SvStatus.inService>
    <cim:SvStatus.ConductingEquipment rdf:resource="#_aecb59fa-9af0-4d30-a865-009c2b35f9cb" />
  </cim:SvStatus>
  <cim:SvStatus rdf:ID="_b83945c9-6b53-4c7e-a5d1-8d875baf57c8">
    <cim:SvStatus.inService>true</cim:SvStatus.inService>
    <cim:SvStatus.ConductingEquipment rdf:resource="#_2b97cb41-b132-4359-ba18-6520d52acd72" />
  </cim:SvStatus>
  <cim:SvStatus rdf:ID="_113b59e1-bea4-4aec-bcd8-76d40c8ad837">
    <cim:SvStatus.inService>true</cim:SvStatus.inService>
    <cim:SvStatus.ConductingEquipment rdf:resource="#_0bc3b6a5-091e-4b8f-b9d9-a34d327473d0" />
  </cim:SvStatus>
  <cim:SvStatus rdf:ID="_f0eddd86-f2fc-442c-8c18-7232f2a1c093">
    <cim:SvStatus.inService>true</cim:SvStatus.inService>
    <cim:SvStatus.ConductingEquipment rdf:resource="#_e1e0da2d-79f4-4ca9-8ca2-62532a91edef" />
  </cim:SvStatus>
  <cim:SvStatus rdf:ID="_c1176eab-c4b5-4a6b-8d98-f2e6703ca50c">
    <cim:SvStatus.inService>true</cim:SvStatus.inService>
    <cim:SvStatus.ConductingEquipment rdf:resource="#_3eae0be8-9a2f-4355-89d6-865b340c2ec9" />
  </cim:SvStatus>
  <cim:SvStatus rdf:ID="_375079ee-6cba-49ca-8fac-77e0ed889552">
    <cim:SvStatus.inService>true</cim:SvStatus.inService>
    <cim:SvStatus.ConductingEquipment rdf:resource="#_c5bac804-64da-4b3a-8bdc-4c199a9d39ac" />
  </cim:SvStatus>
  <cim:SvStatus rdf:ID="_d6c0d5ed-7d0b-4b03-8223-f74067960abd">
    <cim:SvStatus.inService>true</cim:SvStatus.inService>
    <cim:SvStatus.ConductingEquipment rdf:resource="#_6b7dc761-737d-4452-9d3f-de9e14a7c801" />
  </cim:SvStatus>
  <cim:SvStatus rdf:ID="_7012b0da-e8bb-42df-a056-1d7bc0f35f76">
    <cim:SvStatus.inService>true</cim:SvStatus.inService>
    <cim:SvStatus.ConductingEquipment rdf:resource="#_0f02c390-e5bc-4e8f-9936-2d269b8847ad" />
  </cim:SvStatus>
  <cim:SvStatus rdf:ID="_9e053bcd-03c8-42bd-9981-bcde4fe3c915">
    <cim:SvStatus.inService>true</cim:SvStatus.inService>
    <cim:SvStatus.ConductingEquipment rdf:resource="#_315a9d60-b7ef-4652-bc3b-2b8c5d334dcf" />
  </cim:SvStatus>
  <cim:SvStatus rdf:ID="_69f943a3-7a39-49bf-907c-9c54cab2ab80">
    <cim:SvStatus.inService>false</cim:SvStatus.inService>
    <cim:SvStatus.ConductingEquipment rdf:resource="#_d9f23c01-d924-4040-ab48-d5c36ccdf1a3" />
  </cim:SvStatus>
  <cim:SvStatus rdf:ID="_86469717-1699-41e7-9963-bee632e57111">
    <cim:SvStatus.inService>true</cim:SvStatus.inService>
    <cim:SvStatus.ConductingEquipment rdf:resource="#_35ec1a87-3d57-4274-b9c2-ecb120180fab" />
  </cim:SvStatus>
  <cim:SvStatus rdf:ID="_35699556-e37a-49d6-903d-bbe50eb26348">
    <cim:SvStatus.inService>true</cim:SvStatus.inService>
    <cim:SvStatus.ConductingEquipment rdf:resource="#_81ee8901-1cb8-4c51-ae32-d2adc6ad9077" />
  </cim:SvStatus>
  <cim:SvStatus rdf:ID="_cce6d373-c1eb-49ff-a482-e98c0b408b28">
    <cim:SvStatus.inService>true</cim:SvStatus.inService>
    <cim:SvStatus.ConductingEquipment rdf:resource="#_f48344b0-09df-498d-9517-3c51ca3ce8e6" />
  </cim:SvStatus>
  <cim:SvStatus rdf:ID="_3e124e58-5cd6-459d-83b3-4ef43b51a206">
    <cim:SvStatus.inService>true</cim:SvStatus.inService>
    <cim:SvStatus.ConductingEquipment rdf:resource="#_ddb70bc6-7ec9-4042-9816-b7f5a601064e" />
  </cim:SvStatus>
  <cim:SvStatus rdf:ID="_8afaae3b-8693-446c-a590-b22fedc3fea5">
    <cim:SvStatus.inService>true</cim:SvStatus.inService>
    <cim:SvStatus.ConductingEquipment rdf:resource="#_575ed362-86e6-4753-a05c-e0015504a9d1" />
  </cim:SvStatus>
  <cim:SvStatus rdf:ID="_ea3e5feb-da36-47a7-915b-d584ddd00b23">
    <cim:SvStatus.inService>true</cim:SvStatus.inService>
    <cim:SvStatus.ConductingEquipment rdf:resource="#_9c0bdbb8-034f-4a0e-838e-5cdde5c91e9b" />
  </cim:SvStatus>
  <cim:SvStatus rdf:ID="_56263747-4964-4b3b-b4b5-3690cd25793a">
    <cim:SvStatus.inService>true</cim:SvStatus.inService>
    <cim:SvStatus.ConductingEquipment rdf:resource="#_20a4b1b1-5307-471e-85cb-f2b1e059dd4c" />
  </cim:SvStatus>
  <cim:SvStatus rdf:ID="_99d0f13b-22cb-421d-9f07-e38030224001">
    <cim:SvStatus.inService>true</cim:SvStatus.inService>
    <cim:SvStatus.ConductingEquipment rdf:resource="#_9bde615c-44c1-4a7f-8801-72545a4e6c59" />
  </cim:SvStatus>
  <cim:SvStatus rdf:ID="_b1a91049-d4e8-44a7-a534-1958c39b75a8">
    <cim:SvStatus.inService>true</cim:SvStatus.inService>
    <cim:SvStatus.ConductingEquipment rdf:resource="#_535445e8-b782-49a6-87e7-55946e1bbba1" />
  </cim:SvStatus>
  <cim:SvTapStep rdf:ID="_bca293a4-cd97-4fd8-bae4-1bd0d779510c">
    <cim:SvTapStep.position>13</cim:SvTapStep.position>
    <cim:SvTapStep.TapChanger rdf:resource="#_0522ca48-e644-4d3a-9721-22bb0abd1c8b" />
  </cim:SvTapStep>
  <cim:SvTapStep rdf:ID="_c5ffad18-252b-4462-9241-c0c5f625bdb9">
    <cim:SvTapStep.position>17</cim:SvTapStep.position>
    <cim:SvTapStep.TapChanger rdf:resource="#_8de2d157-15d1-42c7-b376-a8ae5b6c0e77" />
  </cim:SvTapStep>
  <cim:SvTapStep rdf:ID="_489747d0-e49b-40a0-8c43-99d15cc1d78b">
    <cim:SvTapStep.position>17</cim:SvTapStep.position>
    <cim:SvTapStep.TapChanger rdf:resource="#_4a8a5456-91ac-4bc9-b8e2-64eeeef78a1a" />
  </cim:SvTapStep>
  <cim:SvPowerFlow rdf:ID="_39cbdc5a-52ed-4ea4-bd51-39935d301e63">
    <cim:SvPowerFlow.p>2</cim:SvPowerFlow.p>
    <cim:SvPowerFlow.q>1</cim:SvPowerFlow.q>
    <cim:SvPowerFlow.Terminal rdf:resource="#_2e6ef544-c98e-44ec-a8de-8c44d2cccc33" />
  </cim:SvPowerFlow>
  <cim:SvPowerFlow rdf:ID="_af149fe2-31db-4697-9992-ddca7a24ce89">
    <cim:SvPowerFlow.p>2</cim:SvPowerFlow.p>
    <cim:SvPowerFlow.q>1</cim:SvPowerFlow.q>
    <cim:SvPowerFlow.Terminal rdf:resource="#_6cd98e8c-ede7-46b1-aa01-7f9f7db26416" />
  </cim:SvPowerFlow>
  <cim:SvPowerFlow rdf:ID="_95a64cb9-9af6-4ba8-b36b-fd2d9fbf2d84">
    <cim:SvPowerFlow.p>0</cim:SvPowerFlow.p>
    <cim:SvPowerFlow.q>0</cim:SvPowerFlow.q>
    <cim:SvPowerFlow.Terminal rdf:resource="#_04684742-c766-11e2-1111-005056c00008" />
  </cim:SvPowerFlow>
  <cim:SvPowerFlow rdf:ID="_38fb12fa-740d-461a-b47b-5bf554cf4d31">
    <cim:SvPowerFlow.p>0</cim:SvPowerFlow.p>
    <cim:SvPowerFlow.q>0</cim:SvPowerFlow.q>
    <cim:SvPowerFlow.Terminal rdf:resource="#_04684742-c766-11e2-2222-005056c00008" />
  </cim:SvPowerFlow>
  <cim:TopologicalIsland rdf:ID="_25bb80f7-d642-4135-8654-24217dfedcdb">
    <cim:IdentifiedObject.name>0</cim:IdentifiedObject.name>
    <cim:TopologicalIsland.AngleRefTopologicalNode rdf:resource="#_c7eda3d2-e92d-4935-8166-5e045d3de045" />
    <cim:TopologicalIsland.TopologicalNodes rdf:resource="#_adee76cd-b2b9-48ac-8fd4-0d205a435f59" />
    <cim:TopologicalIsland.TopologicalNodes rdf:resource="#_87c0d153-e308-4b2b-92a4-4fad53ab1ff9" />
    <cim:TopologicalIsland.TopologicalNodes rdf:resource="#_b3d3b4ad-02af-4490-8748-70f6c9a23734" />
    <cim:TopologicalIsland.TopologicalNodes rdf:resource="#_c7eda3d2-e92d-4935-8166-5e045d3de045" />
    <cim:TopologicalIsland.TopologicalNodes rdf:resource="#_7f5515b2-ca6b-45af-93ee-f196686f0c66" />
    <cim:TopologicalIsland.TopologicalNodes rdf:resource="#_c0adab49-d445-4609-a1a3-ebe4ef297cc8" />
    <cim:TopologicalIsland.TopologicalNodes rdf:resource="#_03163ede-7eec-457f-8641-365982227d7c" />
    <cim:TopologicalIsland.TopologicalNodes rdf:resource="#_c8726716-e182-4373-b83e-8f60070078cb" />
    <cim:TopologicalIsland.TopologicalNodes rdf:resource="#_37edd845-456f-4c3e-98d5-19af0c1cef1e" />
    <cim:TopologicalIsland.TopologicalNodes rdf:resource="#_764e0b8a-f2af-4092-b6aa-b4a19e55db98" />
    <cim:TopologicalIsland.TopologicalNodes rdf:resource="#_cd84fa40-ef63-422d-8ee0-d0a0f806719e" />
  </cim:TopologicalIsland>
  <cim:SvStatus rdf:ID="_2462d35a-8d53-435e-8688-a36fa18876cf">
    <cim:SvStatus.inService>true</cim:SvStatus.inService>
    <cim:SvStatus.ConductingEquipment rdf:resource="#_cc268d3b-fe87-42ee-b48a-9e9d625a8650" />
  </cim:SvStatus>
  <cim:SvStatus rdf:ID="_37dfee25-cc4b-4601-b3a4-3687de8f7d66">
    <cim:SvStatus.inService>true</cim:SvStatus.inService>
    <cim:SvStatus.ConductingEquipment rdf:resource="#_a5a2acc5-c3cd-406c-b061-83a06bcef2f4" />
  </cim:SvStatus>
</rdf:RDF>